mcp_materialize/__init__.py
mcp_materialize/config.py
mcp_materialize/mz_client.py
mcp_materialize/transports.py
mcp_materialize/sql/tools.sql
mcp_materialize-0.3.1.dist-info/METADATA
mcp_materialize-0.3.1.dist-info/WHEEL
mcp_materialize-0.3.1.dist-info/entry_points.txt
mcp_materialize-0.3.1.dist-info/RECORD
