Metadata-Version: 2.4
Name: mcp-materialize
Version: 0.3.1
Summary: A server that exposes Materialize indexes as tools over the Model Context Protocol (MCP)
Author-email: Materialize Inc <support@materialize.com>
Keywords: api,database,materialize,mcp
Requires-Python: >=3.13
Requires-Dist: aiohttp>=3.11.18
Requires-Dist: aiorwlock>=1.5.0
Requires-Dist: fastapi>=0.115.12
Requires-Dist: mcp>=1.10.1
Requires-Dist: psycopg-pool>=3.2.6
Requires-Dist: psycopg[binary]>=3.2.6
Requires-Dist: pytest-asyncio>=1.0.0
Requires-Dist: pytest>=8.4.1
Requires-Dist: pyyaml>=6.0.2
Requires-Dist: requests>=2.32.3
